{"cms":{"mainContent":{"en-AU":{"index":{"content":"a passionate front-end developer who happens to be a combat medic","github":"Github","heading":"Hi, I am Xing Zhi","linkedin":"Linkedin"}},"en-GB":{"index":{"content":"a passionate front-end developer who happens to be a combat medic","github":"Github","heading":"Hi, I am Xing Zhi","linkedin":"Linkedin"}},"en-SG":{"index":{"content":"a passionate front-end developer who happens to be a combat medic","github":"Github","heading":"Hi, I am Xing Zhi","linkedin":"Linkedin"}},"en-US":{"index":{"content":"a passionate front-end developer who happens to be a combat medic","github":"Github","heading":"Hi, I am Xing Zhi","linkedin":"Linkedin"}},"zh-CN":{"index":{"content":"行知是一个有热诚的网络前端开发人员，很刚好的也是一名作战医疗人员","github":"Github","heading":"你好我是行知","linkedin":"领英"}},"zh-HK":{"index":{"content":"行知是一个有热诚的网络前端开发人员，很剛好的也是一名作戰醫療人員","github":"Github","heading":"你好我是行知","linkedin":"领英"}},"zh-TW":{"index":{"content":"行知是一个有热诚的网络前端开发人员，很剛好的也是一名作戰醫療人員","github":"Github","heading":"你好我是行知","linkedin":"领英"}}},"quotes":{"quote":"Our industry does not respect tradition – it only respects innovation.","author":"Satya Nadella"}}}